layers/__init__.py
layers/adapter/__init__.py
layers/adapter/base.py
layers/adapter/communication_manager.py
layers/adapter/autogen/__init__.py
layers/adapter/autogen/adapter.py
layers/adapter/autogen/adapter_simple.py
layers/adapter/autogen/llm_backend.py
layers/adapter/langgraph/__init__.py
layers/adapter/langgraph/adapter.py
layers/adapter/langgraph/adapter_simple.py
layers/adapter/openai/__init__.py
layers/adapter/openai/adapter.py
layers/adapter/openai/agent_wrapper.py
layers/adapter/registry/adapter_registry.py
layers/application/__init__.py
layers/application/communication_manager.py
layers/application/cli/__init__.py
layers/application/cli/agent_factory.py
layers/application/cli/commands.py
layers/application/cli/commands_backup.py
layers/application/cli/enhanced_commands.py
layers/application/cli/enhanced_interactive.py
layers/application/cli/interactive.py
layers/application/cli/main.py
layers/application/orchestration/__init__.py
layers/application/orchestration/lifecycle_manager.py
layers/application/orchestration/load_balancer.py
layers/application/orchestration/orchestrator.py
layers/application/orchestration/service_registry.py
layers/application/web/api_docs_generator.py
layers/application/web/web_manager.py
layers/application/web/backend/main.py
layers/application/web/frontend/adc-web/node_modules/flatted/python/flatted.py
layers/application/web/frontend/adc-web/node_modules/shell-quote/print.py
layers/business/__init__.py
layers/business/communication_manager.py
layers/business/project.py
layers/business/teams/collaboration_manager.py
layers/business/teams/team_engine.py
layers/business/workflows/workflow.py
layers/business/workflows/workflow_engine.py
layers/cognitive/__init__.py
layers/cognitive/cognitive_agent.py
layers/cognitive/communication.py
layers/cognitive/communication_manager.py
layers/cognitive/knowledge_based_agent.py
layers/cognitive/learning.py
layers/cognitive/memory.py
layers/cognitive/memory_persistence.py
zeus_agent-3.0.0.dist-info/licenses/LICENSE
zeus_agent-3.0.0.dist-info/METADATA
zeus_agent-3.0.0.dist-info/WHEEL
zeus_agent-3.0.0.dist-info/entry_points.txt
zeus_agent-3.0.0.dist-info/top_level.txt
zeus_agent-3.0.0.dist-info/RECORD
