Metadata-Version: 2.4
Name: zeus-agent
Version: 3.0.0
Summary: Zeus AI Platform - Next-generation AI Agent Development Platform
Home-page: https://github.com/fpga1988/zeus
Author: Agent Development Center Team
Author-email: Agent Development Center Team <support@zeus-ai.com>
License: MIT License
Project-URL: Homepage, https://github.com/fpga1988/zeus
Project-URL: Repository, https://github.com/fpga1988/zeus
Project-URL: Documentation, https://github.com/fpga1988/zeus/docs
Project-URL: Bug Tracker, https://github.com/fpga1988/zeus/issues
Project-URL: Gitee Mirror, https://gitee.com/fpga1988/zeus
Keywords: ai,agent,artificial-intelligence,machine-learning,nlp,chatbot,automation,framework,platform,fpga,hardware,digital-design,verification,autogen,langchain,crewai,multi-agent
Classifier: Development Status :: 4 - Beta
Classifier: Intended Audience :: Developers
Classifier: Intended Audience :: Science/Research
Classifier: Operating System :: OS Independent
Classifier: Programming Language :: Python :: 3
Classifier: Programming Language :: Python :: 3.8
Classifier: Programming Language :: Python :: 3.9
Classifier: Programming Language :: Python :: 3.10
Classifier: Programming Language :: Python :: 3.11
Classifier: Programming Language :: Python :: 3.12
Classifier: Topic :: Scientific/Engineering :: Artificial Intelligence
Classifier: Topic :: Software Development :: Libraries :: Python Modules
Classifier: Topic :: Software Development :: Code Generators
Classifier: Framework :: AsyncIO
Requires-Python: >=3.8
License-File: LICENSE
Requires-Dist: PyYAML>=6.0
Requires-Dist: numpy>=1.21.0
Requires-Dist: scipy>=1.7.0
Requires-Dist: pandas>=1.3.0
Requires-Dist: sentence-transformers>=2.2.0
Requires-Dist: transformers>=4.21.0
Requires-Dist: torch>=1.12.0
Requires-Dist: torchvision>=0.13.0
Requires-Dist: scikit-learn>=1.1.0
Requires-Dist: chromadb>=0.4.0
Requires-Dist: openai>=1.0.0
Requires-Dist: nltk>=3.7
Requires-Dist: spacy>=3.4.0
Requires-Dist: cryptography>=3.4.8
Requires-Dist: pydantic>=2.0.0
Requires-Dist: aiohttp>=3.8.0
Requires-Dist: asyncio-throttle>=1.0.0
Requires-Dist: sqlalchemy>=1.4.0
Requires-Dist: aiosqlite>=0.17.0
Requires-Dist: python-docx>=0.8.11
Requires-Dist: PyPDF2>=3.0.0
Requires-Dist: markdown>=3.4.0
Requires-Dist: loguru>=0.6.0
Requires-Dist: prometheus-client>=0.14.0
Requires-Dist: httpx>=0.24.0
Requires-Dist: requests>=2.28.0
Requires-Dist: python-dotenv>=1.0.0
Requires-Dist: python-dateutil>=2.8.0
Requires-Dist: jsonschema>=4.17.0
Provides-Extra: dev
Requires-Dist: pytest>=7.0.0; extra == "dev"
Requires-Dist: pytest-asyncio>=0.21.0; extra == "dev"
Requires-Dist: pytest-mock>=3.10.0; extra == "dev"
Requires-Dist: black>=23.0.0; extra == "dev"
Requires-Dist: isort>=5.12.0; extra == "dev"
Requires-Dist: mypy>=1.5.0; extra == "dev"
Requires-Dist: pytest-cov>=4.0.0; extra == "dev"
Provides-Extra: gui
Requires-Dist: PyQt6>=6.0.0; extra == "gui"
Requires-Dist: customtkinter>=5.0.0; extra == "gui"
Provides-Extra: web
Requires-Dist: fastapi>=0.100.0; extra == "web"
Requires-Dist: uvicorn>=0.20.0; extra == "web"
Provides-Extra: vector
Requires-Dist: faiss-cpu>=1.7.0; extra == "vector"
Requires-Dist: hnswlib>=0.7.0; extra == "vector"
Provides-Extra: all
Requires-Dist: pytest>=7.0.0; extra == "all"
Requires-Dist: pytest-asyncio>=0.21.0; extra == "all"
Requires-Dist: pytest-mock>=3.10.0; extra == "all"
Requires-Dist: black>=23.0.0; extra == "all"
Requires-Dist: isort>=5.12.0; extra == "all"
Requires-Dist: mypy>=1.5.0; extra == "all"
Requires-Dist: pytest-cov>=4.0.0; extra == "all"
Requires-Dist: PyQt6>=6.0.0; extra == "all"
Requires-Dist: customtkinter>=5.0.0; extra == "all"
Requires-Dist: fastapi>=0.100.0; extra == "all"
Requires-Dist: uvicorn>=0.20.0; extra == "all"
Requires-Dist: faiss-cpu>=1.7.0; extra == "all"
Requires-Dist: hnswlib>=0.7.0; extra == "all"
Dynamic: author
Dynamic: home-page
Dynamic: license-file
Dynamic: requires-python
